MANIFEST.in
README.rst
README.txt
requirements.txt
setup.py
SweetPy/__init__.py
SweetPy/add_cloud.py
SweetPy/add_cloud_db_option.py
SweetPy/add_handler.py
SweetPy/add_response_header.py
SweetPy/add_sso.py
SweetPy/add_tracker.py
SweetPy/add_zookeeper.py
SweetPy/cloud.py
SweetPy/configurations.py
SweetPy/const.py
SweetPy/func_plus.py
SweetPy/global_share.py
SweetPy/init_program.py
SweetPy/install_apps.py
SweetPy/localaccesslog.py
SweetPy/lock.py
SweetPy/requests.py
SweetPy/scheduler.py
SweetPy/set_http_port.py
SweetPy/set_settingfile.py
SweetPy/setting.py
SweetPy/time_plus.py
SweetPy/tracker.py
SweetPy.egg-info/PKG-INFO
SweetPy.egg-info/SOURCES.txt
SweetPy.egg-info/dependency_links.txt
SweetPy.egg-info/requires.txt
SweetPy.egg-info/top_level.txt
SweetPy/django_middleware/__init__.py
SweetPy/django_middleware/tracker.py
SweetPy/extend/__init__.py
SweetPy/extend/api_view_plus.py
SweetPy/extend/django_runserver_plus.py
SweetPy/extend/mixins_plus.py
SweetPy/extend/rabbitmq_plus.py
SweetPy/extend/response_plus.py
SweetPy/extend/swagger_plus.py
SweetPy/extend/swagger_view.py
SweetPy/extend/view_plus.py
SweetPy/extend/zookeeper_plus.py
SweetPy/geely_auth/__init__.py
SweetPy/geely_auth/geely_sso.py
SweetPy/geely_auth/models.py
SweetPy/geely_auth/migrations/__init__.py
SweetPy/sweet_framework/__init__.py
SweetPy/sweet_framework/sweet_framework_views.py
SweetPy/sweet_framework_cloud/__init__.py
SweetPy/sweet_framework_cloud/sweet_framework_cloud_views.py